form_validation_test0_ti_client/__init__.py
form_validation_test0_ti_client/api_client.py
form_validation_test0_ti_client/api_response.py
form_validation_test0_ti_client/configuration.py
form_validation_test0_ti_client/exceptions.py
form_validation_test0_ti_client/py.typed
form_validation_test0_ti_client/rest.py
form_validation_test0_ti_client/api/__init__.py
form_validation_test0_ti_client/api/pet_api.py
form_validation_test0_ti_client/api/store_api.py
form_validation_test0_ti_client/api/user_api.py
form_validation_test0_ti_client/models/__init__.py
form_validation_test0_ti_client/models/address.py
form_validation_test0_ti_client/models/api_response.py
form_validation_test0_ti_client/models/category.py
form_validation_test0_ti_client/models/customer.py
form_validation_test0_ti_client/models/order.py
form_validation_test0_ti_client/models/pet.py
form_validation_test0_ti_client/models/tag.py
form_validation_test0_ti_client/models/user.py
form_validation_test0_ti_client-1.0.0.dist-info/METADATA
form_validation_test0_ti_client-1.0.0.dist-info/WHEEL
form_validation_test0_ti_client-1.0.0.dist-info/top_level.txt
form_validation_test0_ti_client-1.0.0.dist-info/RECORD
